{"008/24/2021, 15:50:27": [{"edit_history": {"added_under_represented_countries": [], "removed_over_represented_countries": [], "added_over_represented_countries": ["mexico"]}, "Timestamp_frontend": "08/24/2021, 15:50:27", "Timestamp_backend": "08/24/2021, 15:50:29", "edit_message": "The over-represented countries \"mexico\" was added by the user.", "current_over_countries": ["mexico"], "current_under_countries": ["japan"], "suggested_countries": []}], "008/24/2021, 15:50:42": [{"edit_history": {"added_under_represented_countries": [], "removed_over_represented_countries": [], "added_over_represented_countries": ["mexico"]}, "Timestamp_frontend": "08/24/2021, 15:50:42", "Timestamp_backend": "08/24/2021, 15:50:44", "edit_message": "The over-represented countries \"mexico\" was added by the user.", "current_over_countries": ["mexico"], "current_under_countries": ["japan"], "suggested_countries": []}], "aQZ29SmTmNNNl8h0PzFJrNew7ms208/24/2021, 15:51:04": [{"edit_history": {"added_under_represented_countries": [], "removed_over_represented_countries": [], "added_over_represented_countries": ["mexico"]}, "Timestamp_frontend": "08/24/2021, 15:51:04", "Timestamp_backend": "08/24/2021, 15:51:05", "edit_message": "The over-represented countries \"mexico\" was added by the user.", "current_over_countries": ["mexico"], "current_under_countries": ["japan"], "suggested_countries": []}], "aQZ29SmTmNNNl8h0PzFJrNew7ms208/24/2021, 15:51:19": [{"edit_history": {"added_under_represented_countries": [], "removed_over_represented_countries": [], "added_over_represented_countries": ["mexico"]}, "Timestamp_frontend": "08/24/2021, 15:51:19", "Timestamp_backend": "08/24/2021, 15:51:21", "edit_message": "The over-represented countries \"mexico\" was added by the user.", "current_over_countries": ["mexico"], "current_under_countries": ["japan"], "suggested_countries": []}], "aQZ29SmTmNNNl8h0PzFJrNew7ms208/24/2021, 15:51:34": [{"edit_history": {"added_under_represented_countries": [], "removed_over_represented_countries": [], "added_over_represented_countries": ["mexico"]}, "Timestamp_frontend": "08/24/2021, 15:51:34", "Timestamp_backend": "08/24/2021, 15:51:36", "edit_message": "The over-represented countries \"mexico\" was added by the user.", "current_over_countries": ["mexico"], "current_under_countries": ["japan"], "suggested_countries": []}]}